chai_py/__init__.py
chai_py/auth.py
chai_py/chai_bot.py
chai_py/cloud_logs.py
chai_py/defaults.py
chai_py/deployed.py
chai_py/deployment.py
chai_py/error.py
chai_py/logger.py
chai_py/notebook_utils.py
chai_py/packaging.py
chai_py/t_room.py
chai_py/types.py
chaipy-0.4.0.dist-info/LICENSE
chaipy-0.4.0.dist-info/METADATA
chaipy-0.4.0.dist-info/WHEEL
chaipy-0.4.0.dist-info/top_level.txt
chaipy-0.4.0.dist-info/RECORD
