Metadata-Version: 2.1
Name: chaipy
Version: 0.4.0
Summary: A developer interface for creating chatbots for the Chai app.
Home-page: UNKNOWN
Author: Chai
Author-email: dev@chai.ml
License: UNKNOWN
Platform: UNKNOWN
Classifier: Development Status :: 3 - Alpha
Classifier: Intended Audience :: Developers
Classifier: Topic :: Communications :: Chat
Classifier: Natural Language :: English
Classifier: Operating System :: OS Independent
Classifier: Programming Language :: Python :: 3.7
Classifier: License :: OSI Approved :: Apache Software License
Requires-Python: >=3.7
License-File: LICENSE
Requires-Dist: requests (>=2.23.0)
Requires-Dist: typing-extensions (>=3.7.4.3)
Requires-Dist: colorama (>=0.4.4)
Requires-Dist: halo (>=0.0.31)
Requires-Dist: segno (>=1.3.3)
Provides-Extra: notebook
Requires-Dist: nest-asyncio ; extra == 'notebook'
